ovex_python/__init__.py
ovex_python/base.py
ovex_python/client.py
ovex_python/error.py
ovex_py-0.1.0.dist-info/LICENSE
ovex_py-0.1.0.dist-info/METADATA
ovex_py-0.1.0.dist-info/WHEEL
ovex_py-0.1.0.dist-info/top_level.txt
ovex_py-0.1.0.dist-info/RECORD
