Metadata-Version: 2.1
Name: ovex-py
Version: 0.1.0
Summary: A package to interact with OVEX API
Home-page: https://github.com/Quirky-Fox/OVEX-py
Download-URL: https://github.com/Quirky-Fox/OVEX-py/archive/refs/tags/v0.0.1.tar.gz
Author: Duncan Andrew
Author-email: duncan@lumina-x.com
License: MIT
Keywords: OVEX cryptocurrency exchange API
Platform: UNKNOWN
Classifier: Development Status :: 2 - Pre-Alpha
Classifier: Intended Audience :: Financial and Insurance Industry
Classifier: Intended Audience :: Information Technology
Classifier: Intended Audience :: Developers
Classifier: License :: OSI Approved :: MIT License
Classifier: Topic :: Office/Business :: Financial
Classifier: Topic :: Utilities
Classifier: Natural Language :: English
Classifier: Operating System :: POSIX :: Linux
Classifier: Programming Language :: Python :: 3.6
Classifier: Programming Language :: Python :: 3.7
Classifier: Programming Language :: Python :: 3.8
Classifier: Programming Language :: Python :: 3.9
Requires-Python: >=3.6
License-File: LICENSE
Requires-Dist: requests
